mishmash/__about__.py
mishmash/__init__.py
mishmash/__main__.py
mishmash/alembic.ini
mishmash/config.py
mishmash/console.py
mishmash/core.py
mishmash/database.py
mishmash/util.py
mishmash/alembic/README
mishmash/alembic/env.py
mishmash/alembic/script.py.mako
mishmash/alembic/versions/2008219c2861_Album_unique_constraints.py
mishmash/alembic/versions/74df8fa5a35f_initial_autogen_revision.py
mishmash/commands/__init__.py
mishmash/commands/info.py
mishmash/commands/mgmt.py
mishmash/commands/server.py
mishmash/commands/web.py
mishmash/commands/sync/__init__.py
mishmash/commands/sync/_inotify.py
mishmash/commands/sync/sync.py
mishmash/commands/sync/utils.py
mishmash/orm/__init__.py
mishmash/orm/core.py
mishmash/web/__init__.py
mishmash/web/layouts.py
mishmash/web/models.py
mishmash/web/panels.py
mishmash/web/views.py
mishmash/web/static/record150.png
mishmash/web/static/css/mishmash.css
mishmash/web/static/fonts/glyphicons-halflings-regular.eot
mishmash/web/static/fonts/glyphicons-halflings-regular.svg
mishmash/web/static/fonts/glyphicons-halflings-regular.ttf
mishmash/web/static/fonts/glyphicons-halflings-regular.woff
mishmash/web/static/js/mishmash.js
mishmash/web/templates/album.pt
mishmash/web/templates/albums.pt
mishmash/web/templates/artist.pt
mishmash/web/templates/artists.pt
mishmash/web/templates/home.pt
mishmash/web/templates/new_music.pt
mishmash/web/templates/search_results.pt
mishmash/web/templates/layouts/main-layout.pt
mishmash/web/templates/panels/navbar.pt
MishMash-0.3.3.dist-info/LICENSE
MishMash-0.3.3.dist-info/METADATA
MishMash-0.3.3.dist-info/WHEEL
MishMash-0.3.3.dist-info/entry_points.txt
MishMash-0.3.3.dist-info/top_level.txt
MishMash-0.3.3.dist-info/RECORD
