Metadata-Version: 2.1
Name: MishMash
Version: 0.3.3
Summary: Music database and web interface.
Home-page: https://github.com/nicfit/MishMash
Author: Travis Shirk
Author-email: travis@pobox.com
License: GNU GPL v3.0
Download-URL: https://github.com/nicfit/mishmash/releases/downloads/v0.3.3/MishMash-0.3.3.tar.gz
Keywords: music,database
Platform: Any
Classifier: Intended Audience :: End Users/Desktop
Classifier: Operating System :: POSIX
Classifier: Natural Language :: English
Classifier: License :: OSI Approved :: GNU General Public License v3 (GPLv3)
Classifier: Programming Language :: Python
Classifier: Programming Language :: Python :: 3.6
Classifier: Programming Language :: Python :: 3.7
Classifier: Development Status :: 5 - Production/Stable
Requires-Dist: eyeD3
Requires-Dist: nicfit.py
Requires-Dist: SQLAlchemy
Requires-Dist: inotify
Requires-Dist: alembic
Requires-Dist: iso3166
Requires-Dist: pyfiglet
Requires-Dist: sqlalchemy-utils
Requires-Dist: psycopg2-binary
Provides-Extra: web
Requires-Dist: pyramid ; extra == 'web'
Requires-Dist: pyramid-chameleon ; extra == 'web'
Requires-Dist: pyramid-layout ; extra == 'web'
Requires-Dist: pyramid-tm ; extra == 'web'
Requires-Dist: transaction ; extra == 'web'
Requires-Dist: zope.sqlalchemy ; extra == 'web'
Requires-Dist: waitress ; extra == 'web'
Requires-Dist: pyramid-debugtoolbar ; extra == 'web'
Requires-Dist: gevent ; extra == 'web'
Requires-Dist: gunicorn ; extra == 'web'
